C.A./Adder Floating/Lab 0 Floating Point ADDer/finaladdsub.v
// iverilog finaladdsub.v tbfinaladdsub.v -o mina5

module addsub(dataa,datab,add_sub,siwz1,result1,select1);

	input [15:0] dataa;
	input [15:0] datab;
	input add_sub;	  // if this is 1; add; else subtract
	// input clk;
	// output reg [16:0] result
	output [15:0] result1;
	// output cout;
	reg [16:0] result;
	input [4:0]siwz1;//for telling wherher the answer is negative or not

	output  select1;


	always @ (add_sub,dataa,datab)
	begin
		if (add_sub==1)
			begin
			 result <= dataa + datab;
			 // assign cout = result[16];
			 end
		else
			begin
			result <= dataa - datab;
			// assign cout = 0;
			// assign result1 = result[15:0];
			end

			 // result1[15:0] = result[15:0];

	end
	assign result1[15:0] = result[15:0];
	assign select1 = result1[15];


endmodule

C.A./Adder Floating/Lab 0 Floating Point ADDer/tbfinaladdsub.v
// iverilog doubling_recursion.v doubletb.v -o main2
// iverilog finaladdsub.v tbfinaladdsub.v -o mina5
module top ;

// reg [16:1] a;
// reg [16:1] b;

reg [15:0] a;
reg [15:0] b;
reg cin;
reg sgn;
	// Outputs
// wire [16:1] sum;
// wire [16:1] carry1;
// wire [16:0][1:0]carry;
wire [15:0] ans1;
wire cout;
wire select1;
// RCA16bit m1(a,b,cin,sum,cout);
addsub m2(a,b,sgn,5'd16,ans1,select1);

initial
begin

#10;
    a = 16'b0000000000000000;b=16'b0000000000000000;cin = 1'b0;#10;sgn = 1;
    a = 16'b0000000000000001;b=16'b0000000000000000;cin = 1'b0;#10;sgn = 1;
     a = 16'b0000000000000011;b=16'b0000000000000011;cin = 1'b0; #10;sgn = 1;
     a = 16'b0000000000001011;b=16'b0000000000000111;cin = 1'b0; #10;sgn = 1;
     a = 16'b0000001100001111;b=16'b0000000000001111;cin = 1'b0; #10;sgn = 1;
    // a = 16'd12;b=16'd24;cin = 1'b1; #10;sgn = 1;
    a = 16'b0000001100001111;b=16'b0000000000101111;cin = 1'b0; #10;sgn = 1;
    a = 16'b0000001100001111;b=16'b0000000010001011;cin = 1'b0; #10;sgn = 1;
    a = 16'b0000001100001111;b=16'b0000000000011101;cin = 1'b0; #10;sgn = 1;
    a = 16'b0000001100001111;b=16'b0000000001001111;cin = 1'b0; #10;sgn = 1;
    a = 16'b0000000001010110;b=16'b0000000001011101;cin = 1'b0; #10;sgn = 1;
    a = 16'd5560;b=16'd8101;cin = 1'b0; #10;sgn = 1;
    a = 16'd61560;b=16'd60101;cin = 1'b0;sgn = 0; #10;
    a = 16'd1560;b=16'd100;cin = 1'b0; #10;sgn = 0;
    a = 16'd1260;b=16'd1101;cin = 1'b0; #10;sgn = 0;
    a = 16'd1560;b=16'd100;cin = 1'b0; #10;sgn = 0;
    a = 16'd1260;b=16'd2101;cin = 1'b0; #10;sgn = 0;



    // a = 16'd61560;b=16'd64101;cin = 1'b0; #10;sgn = 0;


    // a = 16'd65536;b=16'd65537;cin = 1'b0; #10;sgn = 0;

    // b = !b;


end

initial
begin
// $monitor("time = %2d,")
$monitor("time = %2d,   a=%d, b=%d, Ans=%d,sgn = %d,neg = %d", $time,a, b,ans1,sgn,select1);
$dumpfile("doubling.vcd");
$dumpvars(0,top);
end

endmodule

C.A./Adder Floating/Lab 0 Floating Point ADDer/doubling.vcd
$date
	Wed Jan 15 00:08:21 2020
$end
$version
	Icarus Verilog
$end
$timescale
	1s
$end
$scope module top $end
$var wire 1 ! select1 $end
$var wire 16 " ans1 [15:0] $end
$var reg 16 # a [15:0] $end
$var reg 16 $ b [15:0] $end
$var reg 1 % cin $end
$var reg 1 & sgn $end
$scope module m2 $end
$var wire 1 & add_sub $end
$var wire 16 ' dataa [15:0] $end
$var wire 16 ( datab [15:0] $end
$var wire 5 ) siwz1 [4:0] $end
$var wire 1 ! select1 $end
$var wire 16 * result1 [15:0] $end
$var reg 17 + result [16:0] $end
$upscope $end
$upscope $end
$enddefinitions $end
#0
$dumpvars
bx +
bx *
b10000 )
bx (
bx '
x&
x%
bx $
bx #
bx "
x!
$end
#10
0!
b0 "
b0 *
b0 +
0%
b0 $
b0 (
b0 #
b0 '
#20
b1 "
b1 *
b1 +
b1 #
b1 '
1&
#30
b110 "
b110 *
b110 +
b11 $
b11 (
b11 #
b11 '
#40
b10010 "
b10010 *
b10010 +
b111 $
b111 (
b1011 #
b1011 '
#50
b1100011110 "
b1100011110 *
b1100011110 +
b1111 $
b1111 (
b1100001111 #
b1100001111 '
#60
b1100111110 "
b1100111110 *
b1100111110 +
b101111 $
b101111 (
#70
b1110011010 "
b1110011010 *
b1110011010 +
b10001011 $
b10001011 (
#80
b1100101100 "
b1100101100 *
b1100101100 +
b11101 $
b11101 (
#90
b1101011110 "
b1101011110 *
b1101011110 +
b1001111 $
b1001111 (
#100
b10110011 "
b10110011 *
b10110011 +
b1011101 $
b1011101 (
b1010110 #
b1010110 '
#110
b11010101011101 "
b11010101011101 *
b11010101011101 +
b1111110100101 $
b1111110100101 (
b1010110111000 #
b1010110111000 '
#120
b10110110011 "
b10110110011 *
b10110110011 +
0&
b1110101011000101 $
b1110101011000101 (
b1111000001111000 #
b1111000001111000 '
#130
b10110110100 "
b10110110100 *
b10110110100 +
b1100100 $
b1100100 (
b11000011000 #
b11000011000 '
#140
b10011111 "
b10011111 *
b10011111 +
b10001001101 $
b10001001101 (
b10011101100 #
b10011101100 '
#150
b10110110100 "
b10110110100 *
b10110110100 +
b1100100 $
b1100100 (
b11000011000 #
b11000011000 '
#160
1!
b1111110010110111 "
b1111110010110111 *
b11111110010110111 +
b100000110101 $
b100000110101 (
b10011101100 #
b10011101100 '
