C.A./Adder Floating/Lab 0 Floating Point ADDer/ans.v
module ans(ans,sum,carry);
input [16:0]carry;
input [15:0]sum;
output [16:0]ans;
assign ans[0] = carry[0]^sum[0];
assign ans[1] = carry[1]^sum[1];
assign ans[2] = carry[2]^sum[2];
assign ans[3] = carry[3]^sum[3];
assign ans[4] = carry[4]^sum[4];
assign ans[5] = carry[5]^sum[5];
assign ans[6] = carry[6]^sum[6];
assign ans[7] = carry[7]^sum[7];
assign ans[8] = carry[8]^sum[8];
assign ans[9] = carry[9]^sum[9];
assign ans[10] = carry[10]^sum[10];
assign ans[11] = carry[11]^sum[11];
assign ans[12] = carry[12]^sum[12];
assign ans[13] = carry[13]^sum[13];
assign ans[14] = carry[14]^sum[14];
assign ans[15] = carry[15]^sum[15];
assign ans[16] = carry[16];
endmodule

VLSI/1. Recursion doubling adder/code/coversion.v
module conversion(in,out);
input [16:0][1:0]in;
output [16:0] out;
 
assign out[0] = in[0][1]&in[0][1];
assign out[1] = in[1][1]&in[1][1];
assign out[2] = in[2][1]&in[2][1];
assign out[3] = in[3][1]&in[3][1];
assign out[4] = in[4][1]&in[4][1];
assign out[5] = in[5][1]&in[5][1];
assign out[6] = in[6][1]&in[6][1];
assign out[7] = in[7][1]&in[7][1];
assign out[8] = in[8][1]&in[8][1];
assign out[9] = in[9][1]&in[9][1];
assign out[10] = in[10][1]&in[10][1];
assign out[11] = in[11][1]&in[11][1];
assign out[12] = in[12][1]&in[12][1];
assign out[13] = in[13][1]&in[13][1];
assign out[14] = in[14][1]&in[14][1];
assign out[15] = in[15][1]&in[15][1];
assign out[16] = in[16][1]&in[16][1];
// assign out[0] = in[0][1]&in[0][1];

endmodule

C.A./Adder Floating/Lab 0 Floating Point ADDer/action.v
module action(o1,a,b);
//carry 2 bit x(j)=a x(j+1)=b
input [1:0]a;
input [1:0]b;
output [1:0]o1;

assign o1[1] = b[1]|a[1]&b[0];
assign o1[0] = b[1]|a[0]&b[0];
// assign o1[1] = a[1]|b[1]&a[0];
// assign o1[0] = a[1]|b[0]&a[0];

endmodule // action(carry,carryout)

C.A./Adder Floating/Lab 0 Floating Point ADDer/fivestep.v
// `include "action.v"
module fivestep(carryin,carryout);
input[16:0] [1:0]carryin;
output [16:0] [1:0]carryout;

// 01 bfor 1
// 12 for 2
// 16 jump

assign carryout[0] = carryin[0];
assign carryout[1] = carryin[1];

assign carryout[2] = carryin[2];
assign carryout[3] = carryin[3];

assign carryout[4] = carryin[4];
assign carryout[5] = carryin[5];

assign carryout[6] = carryin[6];
assign carryout[7] = carryin[7];


assign carryout[8] = carryin[8];
assign carryout[9] = carryin[9];

assign carryout[10] = carryin[10];
assign carryout[11] = carryin[11];

assign carryout[12] = carryin[12];
assign carryout[13] = carryin[13];

assign carryout[14] = carryin[14];
assign carryout[15] = carryin[15];

// action m2 (carryout[4],carryin[0],carryin[2]);
// action m3 (carryout[3],carryin[1],carryin[3]);
// action m4 (carryout[4],carryin[0],carryin[4]);
// action m5 (carryout[5],carryin[1],carryin[5]);
// action m6 (carryout[6],carryin[2],carryin[6]);
// action m7 (carryout[7],carryin[3],carryin[7]);
// action m8 (carryout[8],carryin[0],carryin[8]);
// action m9 (carryout[9],carryin[1],carryin[9]);
// action m10 (carryout[10],carryin[2],carryin[10]);
// action m11 (carryout[11],carryin[3],carryin[11]);
// action m12 (carryout[12],carryin[4],carryin[12]);
// action m13(carryout[13],carryin[5],carryin[13]);
// action m14 (carryout[14],carryin[6],carryin[14]);
// action m15(carryout[15],carryin[7],carryin[15]);
action m16(carryout[16],carryin[0],carryin[16]);

endmodule

C.A./Adder Floating/Lab 0 Floating Point ADDer/Lab 0 again imporvement/fourstep.v
// `include "action.v"
module fourstep(carryin,carryout);
input[16:0] [1:0]carryin;
output [16:0] [1:0]carryout;

// 01 bfor 1
// 12 for 2
// 8 jump

assign carryout[0] = carryin[0];
assign carryout[1] = carryin[1];

assign carryout[2] = carryin[2];
assign carryout[3] = carryin[3];

assign carryout[4] = carryin[4];
assign carryout[5] = carryin[5];

assign carryout[6] = carryin[6];
assign carryout[7] = carryin[7];

// action m2 (carryout[4],carryin[0],carryin[2]);
// action m3 (carryout[3],carryin[1],carryin[3]);
// action m4 (carryout[4],carryin[0],carryin[4]);
// action m5 (carryout[5],carryin[1],carryin[5]);
// action m6 (carryout[6],carryin[2],carryin[6]);
// action m7 (carryout[7],carryin[3],carryin[7]);
action m8 (carryout[8],carryin[0],carryin[8]);
action m9 (carryout[9],carryin[1],carryin[9]);
action m10 (carryout[10],carryin[2],carryin[10]);
action m11 (carryout[11],carryin[3],carryin[11]);
action m12 (carryout[12],carryin[4],carryin[12]);
action m13(carryout[13],carryin[5],carryin[13]);
action m14 (carryout[14],carryin[6],carryin[14]);
action m15(carryout[15],carryin[7],carryin[15]);
action m16(carryout[16],carryin[8],carryin[16]);

endmodule

VLSI/1. Recursion doubling adder/code/threestep.v
// `include "action.v"
module threestep(carryin,carryout);
input[16:0] [1:0]carryin;
output [16:0] [1:0]carryout;

// 01 bfor 1
// 12 for 2
//four jump
assign carryout[0] = carryin[0];
assign carryout[1] = carryin[1];

assign carryout[2] = carryin[2];
assign carryout[3] = carryin[3];

// action m2 (carryout[4],carryin[0],carryin[2]);
// action m3 (carryout[3],carryin[1],carryin[3]);
action m4 (carryout[4],carryin[0],carryin[4]);
action m5 (carryout[5],carryin[1],carryin[5]);
action m6 (carryout[6],carryin[2],carryin[6]);
action m7 (carryout[7],carryin[3],carryin[7]);
action m8 (carryout[8],carryin[4],carryin[8]);
action m9 (carryout[9],carryin[5],carryin[9]);
action m10 (carryout[10],carryin[6],carryin[10]);
action m11 (carryout[11],carryin[7],carryin[11]);
action m12 (carryout[12],carryin[8],carryin[12]);
action m13(carryout[13],carryin[9],carryin[13]);
action m14 (carryout[14],carryin[10],carryin[14]);
action m15(carryout[15],carryin[11],carryin[15]);
action m16(carryout[16],carryin[12],carryin[16]);

endmodule

VLSI/1. Recursion doubling adder/code/twostep.v
// `include "action.v"
module twostep(carryin,carryout);
input[16:0] [1:0]carryin;
output [16:0] [1:0]carryout;

// 01 bfor 1
// 12 for 2

assign carryout[0] = carryin[0];
assign carryout[1] = carryin[1];

action m2 (carryout[2],carryin[0],carryin[2]);
action m3 (carryout[3],carryin[1],carryin[3]);
action m4 (carryout[4],carryin[2],carryin[4]);
action m5 (carryout[5],carryin[3],carryin[5]);
action m6 (carryout[6],carryin[4],carryin[6]);
action m7 (carryout[7],carryin[5],carryin[7]);
action m8 (carryout[8],carryin[6],carryin[8]);
action m9 (carryout[9],carryin[7],carryin[9]);
action m10 (carryout[10],carryin[8],carryin[10]);
action m11 (carryout[11],carryin[9],carryin[11]);
action m12 (carryout[12],carryin[10],carryin[12]);
action m13(carryout[13],carryin[11],carryin[13]);
action m14 (carryout[14],carryin[12],carryin[14]);
action m15(carryout[15],carryin[13],carryin[15]);
action m16(carryout[16],carryin[14],carryin[16]);

endmodule

C.A./Adder Floating/Lab 0 Floating Point ADDer/onestep.v
`include "action.v"
module onestep(carryin,carryout);
input[16:0] [1:0]carryin;
output [16:0] [1:0]carryout;

// 01 for 1
// 12 for 2

assign carryout[0] = carryin[0];
action m1 (carryout[1],carryin[0],carryin[1]);
action m2 (carryout[2],carryin[1],carryin[2]);
action m3 (carryout[3],carryin[2],carryin[3]);
action m4 (carryout[4],carryin[3],carryin[4]);
action m5 (carryout[5],carryin[4],carryin[5]);
action m6 (carryout[6],carryin[5],carryin[6]);
action m7 (carryout[7],carryin[6],carryin[7]);
action m8 (carryout[8],carryin[7],carryin[8]);
action m9 (carryout[9],carryin[8],carryin[9]);
action m10 (carryout[10],carryin[9],carryin[10]);
action m11 (carryout[11],carryin[10],carryin[11]);
action m12 (carryout[12],carryin[11],carryin[12]);
action m13(carryout[13],carryin[12],carryin[13]);
action m14 (carryout[14],carryin[13],carryin[14]);
action m15(carryout[15],carryin[14],carryin[15]);
action m16(carryout[16],carryin[15],carryin[16]);

initial
begin

$monitor("time = %2d,  carry =%b,%b,%b ,%b, %b,%b,%b ,%b, %b,%b,%b ,%b, %b,%b,%b ,%b", $time,carryin[15],carryin[14],carryin[13],carryin[12],carryin[11],carryin[10],carryin[9],carryin[8],carryin[7],carryin[6],carryin[5],carryin[4],carryin[3],carryin[2],carryin[1],carryin[0]);
end

endmodule

VLSI/1. Recursion doubling adder/code/doubling_recursion.v
`include "onestep.v"
`include "twostep.v"
`include "threestep.v"
`include "fourstep.v"
`include "fivestep.v"
`include "coversion.v"
`include "ans.v"

module doubling_recursion(a,b,cin,ans1);
input [15:0]a;
input [15:0]b;
input cin;

wire [16:0][1:0]carry ;
wire[16:0][1:0]carry2 ;
wire [16:0][1:0]carry3 ;
wire [16:0][1:0]carry4 ;
wire [16:0][1:0]carry5 ;
wire [16:0][1:0]carry6 ;
wire [15:0]sum;
wire [16:0]carry1;//main carry
output [16:0]ans1;
//k = 00 p = 01 g = 11
// always
// begin
//     if (cin==0)
//         begin
//             carry[0] = 2'b00;
//         end
//     else
//         begin
//             carry[0] = 2'b01;
//         end

// end

 
    assign sum= (a^b);





// coversion to kpg form of carry

 
    // for (i = 1; i < 17; i = i + 1) 
     assign carry[0][1] = cin;
     assign carry[0][0] = cin;

     assign carry[1][1] = a[0]&b[0];

     assign carry[1][0] = a[0]|b[0];

     assign carry[2][1] =  a[1]&b[1];
     assign carry[2][0] =  a[1]|b[1];
     assign carry[3][1] =  a[2]&b[2];
     assign carry[3][0] =  a[2]|b[2];
     assign carry[4][1] =  a[3]&b[3];
     assign carry[4][0] =  a[3]|b[3];
     assign carry[5][1] =  a[4]&b[4];
     assign carry[5][0] =  a[4]|b[4];
     assign carry[6][1] =  a[5]&b[5];
     assign carry[6][0] =  a[5]|b[5];
     assign carry[7][1] =  a[6]&b[6];
     assign carry[7][0] =  a[6]|b[6];
     assign carry[8][1] =  a[7]&b[7];
     assign carry[8][0] =  a[7]|b[7];
 
//       a[8]&b[8];
//  a[8]|b[8];   

     assign carry[9][1] = a[8]&b[8];
     assign carry[9][0] = a[8]|b[8];
     assign carry[10][1] = a[9]&b[9];
     assign carry[10][0] = a[9]|b[9];
     assign carry[11][1] = a[10]&b[10];
     assign carry[11][0] = a[10]|b[10];
     assign carry[12][1] = a[11]&b[11];
     assign carry[12][0] = a[11]|b[11];
     assign carry[13][1] = a[12]&b[12];
     assign carry[13][0] = a[12]|b[12];
     assign carry[14][1] = a[13]&b[13];
     assign carry[14][0] = a[13]|b[13];
     assign carry[15][1] = a[14]&b[14];
     assign carry[15][0] = a[14]|b[14];
     assign carry[16][1] = a[15]&b[15];
     assign carry[16][0] = a[15]|b[15];
    
    // if (a[i-1]&b[i-1])==1) 
    // begin
    //    carry[i] = 2'b0;
    // end
       
    // else if (a[i-1]&b[i-1])==0) 
    // begin
    //    carry[i] = 1'b1;
    // end   

    // else
    //     begin
    //         carry[i] = 1'bx;
    //     end
      

     //makes sequential
     // fork join?

// always  
// //coversion time
// begin
// carry1()    
onestep m11(carry,carry2);

// initial
// begin
// a = 16'b0000000001010110;b=16'b0000000001011101;#10;

// end



// initial
// begin


// // $monitor("time = %2d,  carry =%b,%b,%b ,%b, %b,%b,%b ,%b, %b,%b,%b ,%b, %b,%b,%b ,%b", $time,carryin[15],carryin[14],carryin[13],carryin[12],carryin[11],carryin[10],carryin[9],carryin[8],carryin[7],carryin[6],carryin[5],carryin[4],carryin[3],carryin[2],carryin[1],carryin[0]);
// $monitor("time = %2d,  carry =%b,%b,%b ,%b, %b,%b,%b ,%b, %b,%b,%b ,%b, %b,%b,%b ,%b \n", $time,carry[15],carry[14],carry[13],carry[12],carry[11],carry[10],carry[9],carry[8],carry[7],carry[6],carry[5],carry[4],carry[3],carry[2],carry[1],carry[0]);
// $monitor("time = %2d,  carry2 =%b,%b,%b ,%b, %b,%b,%b ,%b, %b,%b,%b ,%b, %b,%b,%b ,%b", $time,carry2[15],carry2[14],carry2[13],carry2[12],carry2[11],carry2[10],carry2[9],carry2[8],carry2[7],carry2[6],carry2[5],carry2[4],carry2[3],carry2[2],carry2[1],carry2[0]);
// end

// twostep m22(carry2,carry3);
// threestep m33(carry3,carry4);
// fourstep m44(carry5,)
twostep m2(carry2,carry3);
threestep m3(carry3,carry4);
fourstep m4(carry4,carry5);
fivestep m5(carry5,carry6);
conversion m6(carry6,carry1);
ans m7(ans1,sum,carry1);

// end 

//resolve






endmodule

C.A./Adder Floating/Lab 0 Floating Point ADDer/Lab 0 again imporvement/doubletb.v
// iverilog doubling_recursion.v doubletb.v -o main2

module top ;

// reg [16:1] a;
// reg [16:1] b;

reg [15:0] a;
reg [15:0] b;
reg cin;

	// Outputs
// wire [16:1] sum;
// wire [16:1] carry1;
// wire [16:0][1:0]carry;
wire [16:0] ans1;

// RCA16bit m1(a,b,cin,sum,cout);
doubling_recursion m2(a,b,cin,ans1);

initial
begin


    a = 16'b0000000000000000;b=16'b0000000000000000;cin = 1'b0;
    #10
    a = 16'b0000000000000001;b=16'b0000000000000000;cin = 1'b0;#10
     a = 16'b0000000000000011;b=16'b0000000000000011;cin = 1'b0; #10;
     a = 16'b0000000000001011;b=16'b0000000000000111;cin = 1'b0; #10;
     a = 16'b0000001100001111;b=16'b0000000000001111;cin = 1'b0; #10;
    // a = 16'd12;b=16'd24;cin = 1'b1; #10;
    a = 16'b0000001100001111;b=16'b0000000000101111;cin = 1'b0; #10;
    a = 16'b0000001100001111;b=16'b0000000010001011;cin = 1'b0; #10;
    a = 16'b0000001100001111;b=16'b0000000000011101;cin = 1'b0; #10;
    a = 16'b0000001100001111;b=16'b0000000001001111;cin = 1'b0; #10;
    a = 16'b0000000001010110;b=16'b0000000001011101;cin = 1'b0; #10;
    a = 16'd5560;b=16'd8101;cin = 1'b0; #10;
    a = 16'd61560;b=16'd60101;cin = 1'b0; #10;



end

initial
begin
// $monitor("time = %2d,")
$monitor("time = %2d,  cin=%d, a=%d, b=%d, Ans=%d", $time,cin,a, b,ans1);
$dumpfile("doubling.vcd");
$dumpvars(0,top);
end

endmodule

C.A./Adder Floating/Lab 0 Floating Point ADDer/Lab 0 again imporvement/doubling.vcd
$date
	Sun Feb 16 11:40:26 2020
$end
$version
	Icarus Verilog
$end
$timescale
	1s
$end
$scope module top $end
$var wire 17 ! ans1 [16:0] $end
$var reg 16 " a [15:0] $end
$var reg 16 # b [15:0] $end
$var reg 1 $ cin $end
$scope module m2 $end
$var wire 16 % a [15:0] $end
$var wire 16 & b [15:0] $end
$var wire 1 $ cin $end
$var wire 16 ' sum [15:0] $end
$var wire 34 ( carry6 [33:0] $end
$var wire 34 ) carry5 [33:0] $end
$var wire 34 * carry4 [33:0] $end
$var wire 34 + carry3 [33:0] $end
$var wire 34 , carry2 [33:0] $end
$var wire 17 - carry1 [16:0] $end
$var wire 34 . carry [33:0] $end
$var wire 17 / ans1 [16:0] $end
$scope module m11 $end
$var wire 34 0 carryin [33:0] $end
$var wire 34 1 carryout [33:0] $end
$scope module m1 $end
$var wire 2 2 a [1:0] $end
$var wire 2 3 b [1:0] $end
$var wire 2 4 o1 [1:0] $end
$upscope $end
$scope module m10 $end
$var wire 2 5 a [1:0] $end
$var wire 2 6 b [1:0] $end
$var wire 2 7 o1 [1:0] $end
$upscope $end
$scope module m11 $end
$var wire 2 8 a [1:0] $end
$var wire 2 9 b [1:0] $end
$var wire 2 : o1 [1:0] $end
$upscope $end
$scope module m12 $end
$var wire 2 ; a [1:0] $end
$var wire 2 < b [1:0] $end
$var wire 2 = o1 [1:0] $end
$upscope $end
$scope module m13 $end
$var wire 2 > a [1:0] $end
$var wire 2 ? b [1:0] $end
$var wire 2 @ o1 [1:0] $end
$upscope $end
$scope module m14 $end
$var wire 2 A a [1:0] $end
$var wire 2 B b [1:0] $end
$var wire 2 C o1 [1:0] $end
$upscope $end
$scope module m15 $end
$var wire 2 D a [1:0] $end
$var wire 2 E b [1:0] $end
$var wire 2 F o1 [1:0] $end
$upscope $end
$scope module m16 $end
$var wire 2 G a [1:0] $end
$var wire 2 H b [1:0] $end
$var wire 2 I o1 [1:0] $end
$upscope $end
$scope module m2 $end
$var wire 2 J a [1:0] $end
$var wire 2 K b [1:0] $end
$var wire 2 L o1 [1:0] $end
$upscope $end
$scope module m3 $end
$var wire 2 M a [1:0] $end
$var wire 2 N b [1:0] $end
$var wire 2 O o1 [1:0] $end
$upscope $end
$scope module m4 $end
$var wire 2 P a [1:0] $end
$var wire 2 Q b [1:0] $end
$var wire 2 R o1 [1:0] $end
$upscope $end
$scope module m5 $end
$var wire 2 S a [1:0] $end
$var wire 2 T b [1:0] $end
$var wire 2 U o1 [1:0] $end
$upscope $end
$scope module m6 $end
$var wire 2 V a [1:0] $end
$var wire 2 W b [1:0] $end
$var wire 2 X o1 [1:0] $end
$upscope $end
$scope module m7 $end
$var wire 2 Y a [1:0] $end
$var wire 2 Z b [1:0] $end
$var wire 2 [ o1 [1:0] $end
$upscope $end
$scope module m8 $end
$var wire 2 \ a [1:0] $end
$var wire 2 ] b [1:0] $end
$var wire 2 ^ o1 [1:0] $end
$upscope $end
$scope module m9 $end
$var wire 2 _ a [1:0] $end
$var wire 2 ` b [1:0] $end
$var wire 2 a o1 [1:0] $end
$upscope $end
$upscope $end
$scope module m2 $end
$var wire 34 b carryin [33:0] $end
$var wire 34 c carryout [33:0] $end
$scope module m10 $end
$var wire 2 d a [1:0] $end
$var wire 2 e b [1:0] $end
$var wire 2 f o1 [1:0] $end
$upscope $end
$scope module m11 $end
$var wire 2 g a [1:0] $end
$var wire 2 h b [1:0] $end
$var wire 2 i o1 [1:0] $end
$upscope $end
$scope module m12 $end
$var wire 2 j a [1:0] $end
$var wire 2 k b [1:0] $end
$var wire 2 l o1 [1:0] $end
$upscope $end
$scope module m13 $end
$var wire 2 m a [1:0] $end
$var wire 2 n b [1:0] $end
$var wire 2 o o1 [1:0] $end
$upscope $end
$scope module m14 $end
$var wire 2 p a [1:0] $end
$var wire 2 q b [1:0] $end
$var wire 2 r o1 [1:0] $end
$upscope $end
$scope module m15 $end
$var wire 2 s a [1:0] $end
$var wire 2 t b [1:0] $end
$var wire 2 u o1 [1:0] $end
$upscope $end
$scope module m16 $end
$var wire 2 v a [1:0] $end
$var wire 2 w b [1:0] $end
$var wire 2 x o1 [1:0] $end
$upscope $end
$scope module m2 $end
$var wire 2 y a [1:0] $end
$var wire 2 z b [1:0] $end
$var wire 2 { o1 [1:0] $end
$upscope $end
$scope module m3 $end
$var wire 2 | a [1:0] $end
$var wire 2 } b [1:0] $end
$var wire 2 ~ o1 [1:0] $end
$upscope $end
$scope module m4 $end
$var wire 2 !" a [1:0] $end
$var wire 2 "" b [1:0] $end
$var wire 2 #" o1 [1:0] $end
$upscope $end
$scope module m5 $end
$var wire 2 $" a [1:0] $end
$var wire 2 %" b [1:0] $end
$var wire 2 &" o1 [1:0] $end
$upscope $end
$scope module m6 $end
$var wire 2 '" a [1:0] $end
$var wire 2 (" b [1:0] $end
$var wire 2 )" o1 [1:0] $end
$upscope $end
$scope module m7 $end
$var wire 2 *" a [1:0] $end
$var wire 2 +" b [1:0] $end
$var wire 2 ," o1 [1:0] $end
$upscope $end
$scope module m8 $end
$var wire 2 -" a [1:0] $end
$var wire 2 ." b [1:0] $end
$var wire 2 /" o1 [1:0] $end
$upscope $end
$scope module m9 $end
$var wire 2 0" a [1:0] $end
$var wire 2 1" b [1:0] $end
$var wire 2 2" o1 [1:0] $end
$upscope $end
$upscope $end
$scope module m3 $end
$var wire 34 3" carryin [33:0] $end
$var wire 34 4" carryout [33:0] $end
$scope module m10 $end
$var wire 2 5" a [1:0] $end
$var wire 2 6" b [1:0] $end
$var wire 2 7" o1 [1:0] $end
$upscope $end
$scope module m11 $end
$var wire 2 8" a [1:0] $end
$var wire 2 9" b [1:0] $end
$var wire 2 :" o1 [1:0] $end
$upscope $end
$scope module m12 $end
$var wire 2 ;" a [1:0] $end
$var wire 2 <" b [1:0] $end
$var wire 2 =" o1 [1:0] $end
$upscope $end
$scope module m13 $end
$var wire 2 >" a [1:0] $end
$var wire 2 ?" b [1:0] $end
$var wire 2 @" o1 [1:0] $end
$upscope $end
$scope module m14 $end
$var wire 2 A" a [1:0] $end
$var wire 2 B" b [1:0] $end
$var wire 2 C" o1 [1:0] $end
$upscope $end
$scope module m15 $end
$var wire 2 D" a [1:0] $end
$var wire 2 E" b [1:0] $end
$var wire 2 F" o1 [1:0] $end
$upscope $end
$scope module m16 $end
$var wire 2 G" a [1:0] $end
$var wire 2 H" b [1:0] $end
$var wire 2 I" o1 [1:0] $end
$upscope $end
$scope module m4 $end
$var wire 2 J" a [1:0] $end
$var wire 2 K" b [1:0] $end
$var wire 2 L" o1 [1:0] $end
$upscope $end
$scope module m5 $end
$var wire 2 M" a [1:0] $end
$var wire 2 N" b [1:0] $end
$var wire 2 O" o1 [1:0] $end
$upscope $end
$scope module m6 $end
$var wire 2 P" a [1:0] $end
$var wire 2 Q" b [1:0] $end
$var wire 2 R" o1 [1:0] $end
$upscope $end
$scope module m7 $end
$var wire 2 S" a [1:0] $end
$var wire 2 T" b [1:0] $end
$var wire 2 U" o1 [1:0] $end
$upscope $end
$scope module m8 $end
$var wire 2 V" a [1:0] $end
$var wire 2 W" b [1:0] $end
$var wire 2 X" o1 [1:0] $end
$upscope $end
$scope module m9 $end
$var wire 2 Y" a [1:0] $end
$var wire 2 Z" b [1:0] $end
$var wire 2 [" o1 [1:0] $end
$upscope $end
$upscope $end
$scope module m4 $end
$var wire 34 \" carryin [33:0] $end
$var wire 34 ]" carryout [33:0] $end
$scope module m10 $end
$var wire 2 ^" a [1:0] $end
$var wire 2 _" b [1:0] $end
$var wire 2 `" o1 [1:0] $end
$upscope $end
$scope module m11 $end
$var wire 2 a" a [1:0] $end
$var wire 2 b" b [1:0] $end
$var wire 2 c" o1 [1:0] $end
$upscope $end
$scope module m12 $end
$var wire 2 d" a [1:0] $end
$var wire 2 e" b [1:0] $end
$var wire 2 f" o1 [1:0] $end
$upscope $end
$scope module m13 $end
$var wire 2 g" a [1:0] $end
$var wire 2 h" b [1:0] $end
$var wire 2 i" o1 [1:0] $end
$upscope $end
$scope module m14 $end
$var wire 2 j" a [1:0] $end
$var wire 2 k" b [1:0] $end
$var wire 2 l" o1 [1:0] $end
$upscope $end
$scope module m15 $end
$var wire 2 m" a [1:0] $end
$var wire 2 n" b [1:0] $end
$var wire 2 o" o1 [1:0] $end
$upscope $end
$scope module m16 $end
$var wire 2 p" a [1:0] $end
$var wire 2 q" b [1:0] $end
$var wire 2 r" o1 [1:0] $end
$upscope $end
$scope module m8 $end
$var wire 2 s" a [1:0] $end
$var wire 2 t" b [1:0] $end
$var wire 2 u" o1 [1:0] $end
$upscope $end
$scope module m9 $end
$var wire 2 v" a [1:0] $end
$var wire 2 w" b [1:0] $end
$var wire 2 x" o1 [1:0] $end
$upscope $end
$upscope $end
$scope module m5 $end
$var wire 34 y" carryin [33:0] $end
$var wire 34 z" carryout [33:0] $end
$scope module m16 $end
$var wire 2 {" a [1:0] $end
$var wire 2 |" b [1:0] $end
$var wire 2 }" o1 [1:0] $end
$upscope $end
$upscope $end
$scope module m6 $end
$var wire 34 ~" in [33:0] $end
$var wire 17 !# out [16:0] $end
$upscope $end
$scope module m7 $end
$var wire 17 "# carry [16:0] $end
$var wire 16 ## sum [15:0] $end
$var wire 17 $# ans [16:0] $end
$upscope $end
$upscope $end
$upscope $end
$enddefinitions $end
#0
$dumpvars
b0 $#
b0 ##
b0 "#
b0 !#
b0 ~"
b0 }"
b0 |"
b0 {"
b0 z"
b0 y"
b0 x"
b0 w"
b0 v"
b0 u"
b0 t"
b0 s"
b0 r"
b0 q"
b0 p"
b0 o"
b0 n"
b0 m"
b0 l"
b0 k"
b0 j"
b0 i"
b0 h"
b0 g"
b0 f"
b0 e"
b0 d"
b0 c"
b0 b"
b0 a"
b0 `"
b0 _"
b0 ^"
b0 ]"
b0 \"
b0 ["
b0 Z"
b0 Y"
b0 X"
b0 W"
b0 V"
b0 U"
b0 T"
b0 S"
b0 R"
b0 Q"
b0 P"
b0 O"
b0 N"
b0 M"
b0 L"
b0 K"
b0 J"
b0 I"
b0 H"
b0 G"
b0 F"
b0 E"
b0 D"
b0 C"
b0 B"
b0 A"
b0 @"
b0 ?"
b0 >"
b0 ="
b0 <"
b0 ;"
b0 :"
b0 9"
b0 8"
b0 7"
b0 6"
b0 5"
b0 4"
b0 3"
b0 2"
b0 1"
b0 0"
b0 /"
b0 ."
b0 -"
b0 ,"
b0 +"
b0 *"
b0 )"
b0 ("
b0 '"
b0 &"
b0 %"
b0 $"
b0 #"
b0 ""
b0 !"
b0 ~
b0 }
b0 |
b0 {
b0 z
b0 y
b0 x
b0 w
b0 v
b0 u
b0 t
b0 s
b0 r
b0 q
b0 p
b0 o
b0 n
b0 m
b0 l
b0 k
b0 j
b0 i
b0 h
b0 g
b0 f
b0 e
b0 d
b0 c
b0 b
b0 a
b0 `
b0 _
b0 ^
b0 ]
b0 \
b0 [
b0 Z
b0 Y
b0 X
b0 W
b0 V
b0 U
b0 T
b0 S
b0 R
b0 Q
b0 P
b0 O
b0 N
b0 M
b0 L
b0 K
b0 J
b0 I
b0 H
b0 G
b0 F
b0 E
b0 D
b0 C
b0 B
b0 A
b0 @
b0 ?
b0 >
b0 =
b0 <
b0 ;
b0 :
b0 9
b0 8
b0 7
b0 6
b0 5
b0 4
b0 3
b0 2
b0 1
b0 0
b0 /
b0 .
b0 -
b0 ,
b0 +
b0 *
b0 )
b0 (
b0 '
b0 &
b0 %
0$
b0 #
b0 "
b0 !
$end
#10
b1 !
b1 /
b1 $#
b1 3
b1 J
b100 .
b100 0
b1 '
b1 ##
b1 "
b1 %
#20
b110 -
b110 !#
b110 "#
b11 ^"
b111100 (
b111100 z"
b111100 ~"
b11 P"
b111100 )
b111100 ]"
b111100 y"
b11 v"
b11 {
b111100 *
b111100 4"
b111100 \"
b11 M"
b111100 +
b111100 c
b111100 3"
b11 |
b11 z
b11 !"
b11 4
b111100 ,
b111100 1
b111100 b
b11 L
b11 3
b11 J
b110 !
b110 /
b110 $#
b11 K
b11 M
b111100 .
b111100 0
b0 '
b0 ##
b11 #
b11 &
b11 "
b11 %
#30
b11110 -
b11110 !#
b11110 "#
b11 d"
b11 L"
b1111111100 (
b1111111100 z"
b1111111100 ~"
b1111111100 )
b1111111100 ]"
b1111111100 y"
b11 a"
b11 K"
b11 V"
b1111111100 *
b1111111100 4"
b1111111100 \"
b11 S"
b11 #"
b1111111100 +
b1111111100 c
b1111111100 3"
b11 ~
b11 }
b11 $"
b1 ""
b1 '"
b11 O
b111111100 ,
b111111100 1
b111111100 b
b1 R
b1 N
b1 P
b10010 !
b10010 /
b10010 $#
b1 Q
b1 S
b101111100 .
b101111100 0
b1100 '
b1100 ##
b111 #
b111 &
b1011 "
b1011 %
#40
b1 e
b1 j
b11 ""
b11 '"
b1 7
b100000000001111111100 ,
b100000000001111111100 1
b100000000001111111100 b
b11 R
b11 Q
b11 S
b1100011110 !
b1100011110 /
b1100011110 $#
b11 N
b11 P
b1 `
b1 5
b1 6
b1 8
b101000000001111111100 .
b101000000001111111100 0
b1100000000 '
b1100000000 ##
b1111 #
b1111 &
b1100001111 "
b1100001111 %
#50
b1100111110 !
b1100111110 /
b1100111110 $#
b1 W
b1 Y
b101000001001111111100 .
b101000001001111111100 0
b1100100000 '
b1100100000 ##
b101111 #
b101111 &
#60
b1 1"
b1 g
b101000000001111111100 ,
b101000000001111111100 1
b101000000001111111100 b
b1 a
b1110011010 !
b1110011010 /
b1110011010 $#
b1 N
b1 P
b0 W
b0 Y
b1 ]
b1 _
b101010000001101111100 .
b101010000001101111100 0
b1110000100 '
b1110000100 ##
b10001011 #
b10001011 &
#70
b111110 -
b111110 !#
b111110 "#
b111111111100 (
b111111111100 z"
b111111111100 ~"
b111111111100 )
b111111111100 ]"
b111111111100 y"
b11 g"
b111111111100 *
b111111111100 4"
b111111111100 \"
b11 O"
b11 N"
b11 Y"
b111111111100 +
b111111111100 c
b111111111100 3"
b11 &"
b11 %"
b11 *"
b0 1"
b0 g
b11 U
b100000000111111111100 ,
b100000000111111111100 1
b100000000111111111100 b
b0 a
b1100101100 !
b1100101100 /
b1100101100 $#
b1 K
b1 M
b11 N
b11 P
b1 T
b1 V
b0 ]
b0 _
b101000000011111011100 .
b101000000011111011100 0
b1100010010 '
b1100010010 ##
b11101 #
b11101 &
#80
b11110 -
b11110 !#
b11110 "#
b1111111100 (
b1111111100 z"
b1111111100 ~"
b1111111100 )
b1111111100 ]"
b1111111100 y"
b0 g"
b1111111100 *
b1111111100 4"
b1111111100 \"
b0 O"
b0 N"
b0 Y"
b1111111100 +
b1111111100 c
b1111111100 3"
b0 &"
b0 %"
b0 *"
b100000000001111111100 ,
b100000000001111111100 1
b100000000001111111100 b
b0 U
b1101011110 !
b1101011110 /
b1101011110 $#
b11 K
b11 M
b0 T
b0 V
b1 Z
b1 \
b101000100001111111100 .
b101000100001111111100 0
b1101000000 '
b1101000000 ##
b1001111 #
b1001111 &
