C.A./Adder Floating/Lab 0 Floating Point ADDer/LAb0/onlysub.v
module addsub
(
	input [15:0] dataa,
	input [15:0] datab,
	input clk,
	output reg [16:0] result
);

	// always @ (posedge clk)
	always @ (posedge clk)

	begin
		// if (add_sub)
			// result <= dataa + datab;
		// else
			result <= dataa - datab;
	end

endmodule

C.A./Adder Floating/Lab 0 Floating Point ADDer/LAb0/asubtb.v
// iverilog doubling_recursion.v doubletb.v -o main2

module top ;

// reg [16:1] a;
// reg [16:1] b;

reg [15:0] a;
reg [15:0] b;
// reg cin;
reg clk;
	// Outputs
// wire [16:1] sum;
// wire [16:1] carry1;
// wire [16:0][1:0]carry;
wire [16:0] ans1;

// RCA16bit m1(a,b,cin,sum,cout);
addsub m2(a,b,clk,ans1);

initial
begin
    clk = 1;

    a = 16'b0000000000000000;b=16'b0000000000000000;//cin = 1'b0;
    #10
    a = 16'b0000000000000001;b=16'b0000000000000000;//cin = 1'b0;
    #10;
     a = 16'b0000000000000011;b=16'b0000000000000011;//cin = 1'b0;
     #10;
     a = 16'b0000000000001011;b=16'b0000000000000111;//cin = 1'b0;
     #10;
     a = 16'b0000001100001111;b=16'b0000000000001111;//cin = 1'b0;
     #10;
    // a = 16'd12;b=16'd24;//cin = 1'b1;
    #10;
    a = 16'b0000001100001111;b=16'b0000000000101111;//cin = 1'b0;
    #10;
    a = 16'b0000001100001111;b=16'b0000000010001011;//cin = 1'b0;
    #10;
    a = 16'b0000001100001111;b=16'b0000000000011101;//cin = 1'b0;
    #10;
    a = 16'b0000001100001111;b=16'b0000000001001111;//cin = 1'b0;
    #10;
    a = 16'b0000000001010110;b=16'b0000000001011101;//cin = 1'b0;
    #10;
    a = 16'd5560;b=16'd8101;//cin = 1'b0;
    #10;
    a = 16'd61560;b=16'd60101;//cin = 1'b0;
    #10;
    // b = !b;
    clk = 0;


end

initial
begin
// $monitor("time = %2d,")
$monitor("time = %2d,   a=%d, b=%d, Ans=%b", $time,a, b,ans1);
$dumpfile("addsub1.vcd");
$dumpvars(0,top);
end

endmodule

C.A./Adder Floating/Lab 0 Floating Point ADDer/LAb0/addsub1.vcd
$date
	Tue Jan 14 15:17:31 2020
$end
$version
	Icarus Verilog
$end
$timescale
	1s
$end
$scope module top $end
$var wire 17 ! ans1 [16:0] $end
$var reg 16 " a [15:0] $end
$var reg 16 # b [15:0] $end
$var reg 1 $ clk $end
$scope module m2 $end
$var wire 1 $ clk $end
$var wire 16 % dataa [15:0] $end
$var wire 16 & datab [15:0] $end
$var reg 17 ' result [16:0] $end
$upscope $end
$upscope $end
$enddefinitions $end
#0
$dumpvars
b0 '
b0 &
b0 %
1$
b0 #
b0 "
b0 !
$end
#10
b1 "
b1 %
#20
b11 #
b11 &
b11 "
b11 %
#30
b111 #
b111 &
b1011 "
b1011 %
#40
b1111 #
b1111 &
b1100001111 "
b1100001111 %
#60
b101111 #
b101111 &
#70
b10001011 #
b10001011 &
#80
b11101 #
b11101 &
#90
b1001111 #
b1001111 &
#100
b1011101 #
b1011101 &
b1010110 "
b1010110 %
#110
b1111110100101 #
b1111110100101 &
b1010110111000 "
b1010110111000 %
#120
b1110101011000101 #
b1110101011000101 &
b1111000001111000 "
b1111000001111000 %
