C.A./Adder Floating/Lab 0 Floating Point ADDer/LAb0/addsub.v

// iverilog addsub.v addsub_tb.v -o pl1

module addsub
(
	input [7:0] dataa,
	input [7:0] datab,
	input add_sub,	  // if this is 1, add; else subtract
	// input clk,
	// output reg selec1,
	output sign12,
	output [8:0]asnwer
);
reg [8:0] result;
reg selec1;
reg [7:0]tmptobeadded = 8'b00000001;

	// always @ (posedge clk)
	always @(*)
	begin
		if (add_sub)
			begin
			result = dataa + datab;
			selec1 = 0;
			end
			// self
		else
			// result <= dataa - datab;
			begin
			result = dataa - datab;

			selec1 = 1&result[8];
			end
			// always @ ( result )
			// begin
			//
			// if (result>256)
			// begin
			// 	result = -result;
			// end
			// end

	end
	// always @ ( result ) begin
	 assign asnwer[0] = !result[0]&&selec1||result[0]&&!selec1;
	 assign asnwer[1] = !result[1]&&selec1||result[1]&&!selec1;
	 assign asnwer[2] = !result[2]&&selec1||result[2]&&!selec1;
	 assign asnwer[3] = !result[3]&&selec1||result[3]&&!selec1;
	 assign asnwer[4] = !result[4]&&selec1||result[4]&&!selec1;
	 assign asnwer[5] = !result[5]&&selec1||result[5]&&!selec1;
	 assign asnwer[6] = !result[6]&&selec1||result[6]&&!selec1;
	 assign asnwer[7] = !result[7]&&selec1||result[7]&&!selec1;
	 assign asnwer[8] = !result[8]&&selec1||result[8]&&!selec1;



	// end
	// if ((selec1&&!add_sub)==1)
	// begin
	// 		assign  answer = -result;
	// // 		result = -result;
	// 	// asnwer = asnwer+tmptobeadded;
	// end

	assign sign12 = selec1&&!add_sub;


endmodule

C.A./Adder Floating/Lab 0 Floating Point ADDer/LAb0/addsub_tb.v
// iverilog addsub.v addsub_tb.v -o pl1


module top;
reg [7:0] a;
reg [7:0] b;
reg add_sub;	  // if this is 1, add; else subtract
// input clk,
wire selec1;
wire [8:0] result;


addsub s1(a,b,add_sub,selec1,result);
// addsub s1(a,b,add_sub,select1,result);


initial
begin

a = 8'b00000011;b = 8'b00000010;add_sub = 1;#10;
a = 8'b00000101;b = 8'b00000110;add_sub = 1;#10;

a = 8'b00000111;b = 8'b00000111;add_sub = 1;#10;
a = 8'b00000111;b = 8'b00001111;add_sub = 0;#10;
a = 8'b00000111;b = 8'b00000111;add_sub = 1;#10;


a = 8'b00001111;b = 8'b00001010;add_sub = 0;#10;
a = 8'b11111100; b= 8'd252;add_sub = 1;#10;
a = 8'b11111110; b= 8'd252;add_sub = 0;#10;

a = 8'b11111100; b= 8'd255;add_sub = 0;#10;

a = 8'b11111110; b= 8'd22;add_sub = 1;#10;



// a = 16'b0000000000000011;b=16'b0000000000000010;cin = 1'b0; #10;sgn = 1;
//
//     a = 16'b0000000000000000;b=16'b0000000000000000;cin = 1'b0;#10;sgn = 1;
//     a = 16'b0000000000000001;b=16'b0000000000000000;cin = 1'b0;#10;sgn = 1;
//      a = 16'b0000000000001011;b=16'b0000000000000111;cin = 1'b0; #10;sgn = 1;
//      a = 16'b0000001100001111;b=16'b0000000000001111;cin = 1'b0; #10;sgn = 1;
//     // a = 16'd12;b=16'd24;cin = 1'b1; #10;sgn = 1;
//     a = 16'b0000101100001111;b=16'b0000000000101111;cin = 1'b0; #10;sgn = 1;
//     a = 16'b0000101100001111;b=16'b0000000010001011;cin = 1'b0; #10;sgn = 1;
//     a = 16'b0001001100001111;b=16'b0000000000011101;cin = 1'b0; #10;sgn = 1;
//     a = 16'b0001001100001111;b=16'b0000000001001111;cin = 1'b0; #10;sgn = 1;
//     a = 16'b0001000001010110;b=16'b0000000001011101;cin = 1'b0; #10;sgn = 1;
//     a = 16'd5560;b=16'd101;cin = 1'b0; #10;sgn = 0;
//     a = 16'd61560;b=16'd60101;cin = 1'b0; #10;sgn = 0;
//     a = 16'd65530;b=16'd60101;cin = 1'b0; #10;sgn = 0;

    // b = !b;


end

initial
begin
// $monitor("time = %2d,")
$monitor("time = %2d,  sign=%d, a=%d, b=%d Ans=%d sign = %d", $time,add_sub,a, b,result,selec1);
$dumpfile("dadderng.vcd");
$dumpvars(0,top);
end



endmodule // top

C.A./Adder Floating/Lab 0 Floating Point ADDer/LAb0/dadderng.vcd
$date
	Tue Jan 21 22:08:33 2020
$end
$version
	Icarus Verilog
$end
$timescale
	1s
$end
$scope module top $end
$var wire 1 ! selec1 $end
$var wire 9 " result [8:0] $end
$var reg 8 # a [7:0] $end
$var reg 1 $ add_sub $end
$var reg 8 % b [7:0] $end
$scope module s1 $end
$var wire 1 $ add_sub $end
$var wire 8 & dataa [7:0] $end
$var wire 8 ' datab [7:0] $end
$var wire 1 ! sign12 $end
$var wire 9 ( asnwer [8:0] $end
$var reg 9 ) result [8:0] $end
$var reg 1 * selec1 $end
$var reg 8 + tmptobeadded [7:0] $end
$upscope $end
$upscope $end
$enddefinitions $end
#0
$dumpvars
b1 +
0*
b101 )
b101 (
b10 '
b11 &
b10 %
1$
b11 #
b101 "
0!
$end
#10
b1011 "
b1011 (
b1011 )
b110 %
b110 '
b101 #
b101 &
#20
b1110 "
b1110 (
b1110 )
b111 %
b111 '
b111 #
b111 &
#30
b111 "
b111 (
1!
1*
b111111000 )
0$
b1111 %
b1111 '
#40
b1110 "
b1110 (
0!
0*
b1110 )
1$
b111 %
b111 '
#50
b101 "
b101 (
b101 )
0$
b1010 %
b1010 '
b1111 #
b1111 &
#60
b111111000 "
b111111000 (
b111111000 )
1$
b11111100 %
b11111100 '
b11111100 #
b11111100 &
#70
b10 "
b10 (
b10 )
0$
b11111110 #
b11111110 &
#80
1!
1*
b111111101 )
b11111111 %
b11111111 '
b11111100 #
b11111100 &
#90
b100010100 "
b100010100 (
0!
0*
b100010100 )
1$
b10110 %
b10110 '
b11111110 #
b11111110 &
