C.A./Adder Floating/Lab 0 Floating Point ADDer/Lab 0 again imporvement/add12sub.v

// iverilog addsub.v addsub_tb.v -o pl1
// iverilog add12sub.v addsub_tb.v -o mit
//
// module addsubexp
// (
// 	input [4:0] dataa,
// 	input [4:0] datab,
// 	input add_sub,	  // if this is 1, add; else subtract
// 	// input clk,
// 	// output reg selec1,
// 	output sign12,//output is 1 then negative(answer is 1 less) else positive
// 	output [5:0]asnwer
// );

module addsubexp(dataa,datab,add_sub,sign12,asnwer);
input [4:0] dataa;
input [4:0] datab;
input add_sub;	  // if this is 1; add; else subtract
// input clk,
// output reg selec1,
output sign12;//output is 1 then negative(answer is 1 less) else positive
output [5:0]asnwer;

reg [5:0] result;
reg selec1;
// reg [4:0]tmptobeadded = 5'b00001;
// assign add_sub = 1'b0;
	// always @ (posedge clk)
	always @(*)
	begin
		if (add_sub)
			begin
			result = dataa + datab;
			selec1 = 0;
			end
			// self
		else
			// result <= dataa - datab;
			begin
			result = dataa - datab;

			selec1 = 1&result[5];
			end
			// always @ ( result )
			// begin
			//
			// if (result>256)
			// begin
			// 	result = -result;
			// end
			// end

	end
	// always @ ( result ) begin
	 assign asnwer[0] = !result[0]&&selec1||result[0]&&!selec1;
	 assign asnwer[1] = !result[1]&&selec1||result[1]&&!selec1;
	 assign asnwer[2] = !result[2]&&selec1||result[2]&&!selec1;
	 assign asnwer[3] = !result[3]&&selec1||result[3]&&!selec1;
	 assign asnwer[4] = !result[4]&&selec1||result[4]&&!selec1;
	 assign asnwer[5] = !result[5]&&selec1||result[5]&&!selec1;
	 // assign asnwer[6] = !result[6]&&selec1||result[6]&&!selec1;
	 // assign asnwer[7] = !result[7]&&selec1||result[7]&&!selec1;
	 // assign asnwer[8] = !result[8]&&selec1||result[8]&&!selec1;



	// end
	// if ((selec1&&!add_sub)==1)
	// begin
	// 		assign  answer = -result;
	// // 		result = -result;
	// 	// asnwer = asnwer+tmptobeadded;
	// end

	assign sign12 = selec1&&!add_sub;


endmodule

C.A./Adder Floating/Lab 0 Floating Point ADDer/Submition/addsub_tb.v
// iverilog add12sub.v addsub_tb.v -o mit

module top;
reg [4:0] a;
reg [4:0] b;
reg add_sub;	  // if this is 1, add; else subtract
// input clk,
wire selec1;
wire [5:0] result;


addsubexp s1(a,b,add_sub,selec1,result);
// addsub s1(a,b,add_sub,select1,result);


initial
begin

a = 5'b00011;b = 5'b00010;add_sub = 1;#10;
a = 5'b00101;b = 5'b00110;add_sub = 0;#10;

a = 5'b00111;b = 5'b00111;add_sub = 1;#10;
a = 5'b00111;b = 5'b01111;add_sub = 0;#10;
a = 5'b00111;b = 5'b00011;add_sub = 1;#10;


a = 5'b01111;b = 5'b00000;add_sub = 0;#10;
a = 5'b11100; b= 5'd22;add_sub = 1;#10;
a = 5'b11110; b= 5'd12;add_sub = 0;#10;

a = 5'b10100; b= 5'd15;add_sub = 0;#10;

a = 5'b11110; b= 5'd22;add_sub = 1;#10;



// a = 16'b0000000000000011;b=16'b0000000000000010;cin = 1'b0; #10;sgn = 1;
//
//     a = 16'b0000000000000000;b=16'b0000000000000000;cin = 1'b0;#10;sgn = 1;
//     a = 16'b0000000000000001;b=16'b0000000000000000;cin = 1'b0;#10;sgn = 1;
//      a = 16'b0000000000001011;b=16'b0000000000000111;cin = 1'b0; #10;sgn = 1;
//      a = 16'b0000001100001111;b=16'b0000000000001111;cin = 1'b0; #10;sgn = 1;
//     // a = 16'd12;b=16'd24;cin = 1'b1; #10;sgn = 1;
//     a = 16'b0000101100001111;b=16'b0000000000101111;cin = 1'b0; #10;sgn = 1;
//     a = 16'b0000101100001111;b=16'b0000000010001011;cin = 1'b0; #10;sgn = 1;
//     a = 16'b0001001100001111;b=16'b0000000000011101;cin = 1'b0; #10;sgn = 1;
//     a = 16'b0001001100001111;b=16'b0000000001001111;cin = 1'b0; #10;sgn = 1;
//     a = 16'b0001000001010110;b=16'b0000000001011101;cin = 1'b0; #10;sgn = 1;
//     a = 16'd5560;b=16'd101;cin = 1'b0; #10;sgn = 0;
//     a = 16'd61560;b=16'd60101;cin = 1'b0; #10;sgn = 0;
//     a = 16'd65530;b=16'd60101;cin = 1'b0; #10;sgn = 0;

    // b = !b;


end

initial
begin
// $monitor("time = %2d,")
$monitor("time = %2d,  addorsub=%d, a=%d, b=%d Ans=%d sign = %d", $time,add_sub,a, b,result,selec1);
$dumpfile("daddering.vcd");
$dumpvars(0,top);
end



endmodule // top

C.A./Adder Floating/Lab 0 Floating Point ADDer/Main Work/daddering.vcd
$date
	Tue Jan 28 15:50:43 2020
$end
$version
	Icarus Verilog
$end
$timescale
	1s
$end
$scope module top $end
$var wire 1 ! selec1 $end
$var wire 6 " result [5:0] $end
$var reg 5 # a [4:0] $end
$var reg 1 $ add_sub $end
$var reg 5 % b [4:0] $end
$scope module s1 $end
$var wire 1 $ add_sub $end
$var wire 5 & dataa [4:0] $end
$var wire 5 ' datab [4:0] $end
$var wire 1 ! sign12 $end
$var wire 6 ( asnwer [5:0] $end
$var reg 6 ) result [5:0] $end
$var reg 1 * selec1 $end
$upscope $end
$upscope $end
$enddefinitions $end
#0
$dumpvars
0*
b101 )
b101 (
b10 '
b11 &
b10 %
1$
b11 #
b101 "
0!
$end
#10
b0 "
b0 (
1!
1*
b111111 )
0$
b110 %
b110 '
b101 #
b101 &
#20
b1110 "
b1110 (
0!
0*
b1110 )
1$
b111 %
b111 '
b111 #
b111 &
#30
b111 "
b111 (
1!
1*
b111000 )
0$
b1111 %
b1111 '
#40
b1010 "
b1010 (
0!
0*
b1010 )
1$
b11 %
b11 '
#50
b1111 "
b1111 (
b1111 )
0$
b0 %
b0 '
b1111 #
b1111 &
#60
b110010 "
b110010 (
b110010 )
1$
b10110 %
b10110 '
b11100 #
b11100 &
#70
b10010 "
b10010 (
b10010 )
0$
b1100 %
b1100 '
b11110 #
b11110 &
#80
b101 "
b101 (
b101 )
b1111 %
b1111 '
b10100 #
b10100 &
#90
b110100 "
b110100 (
b110100 )
1$
b10110 %
b10110 '
b11110 #
b11110 &
