C.A./Adder Floating/Lab 0 Floating Point ADDer/Submition/add1toval.v
// iverilog add1toval.v  add1valtb.v -o oknwe

module add1toval(dataa,e1nable,asnwer);
input [11:0] dataa;
input e1nable;	  // if this is 1; add; else subtract
output [11:0]asnwer;
reg [11:0] result;

	always @(*)
	begin
		if (e1nable)
			begin
			result = dataa + 1'b1;
			end
			// self
    else
      begin
      result = dataa ;

      end

	end

assign asnwer = result;
endmodule

C.A./Adder Floating/Lab 0 Floating Point ADDer/Main Work/expaddsub.v
// iverilog expaddsub.v expaddsubtb.v -o p4jul
`include "add1toval.v"
module addsub
(
	input [10:0] dataa,
	input [10:0] datab,
	input add_sub,	  // if this is 1, add; else subtract
	// input clk,
	// output reg selec1,
	output sign12,//output is 1 then negative(answer is 1 less) else positive
	output [11:0]answer
);
reg [11:0] result;
reg selec1;
wire [11:0]temp;
// reg [10:0]tmptobeadded = 10'b0000000001;

	// always @ (posedge clk)
	always @(*)
	begin
		if (add_sub)
			begin
			result = dataa + datab;
			selec1 = 0;
			end
			// self
		else
			// result <= dataa - datab;
			begin
			result = dataa - datab;

			selec1 = 1&result[11];
			end

	end
	// always @ ( result ) begin
	 assign temp[0] = !result[0]&&selec1||result[0]&&!selec1;
	 assign temp[1] = !result[1]&&selec1||result[1]&&!selec1;
	 assign temp[2] = !result[2]&&selec1||result[2]&&!selec1;
	 assign temp[3] = !result[3]&&selec1||result[3]&&!selec1;
	 assign temp[4] = !result[4]&&selec1||result[4]&&!selec1;
	 assign temp[5] = !result[5]&&selec1||result[5]&&!selec1;
	 assign temp[6] = !result[6]&&selec1||result[6]&&!selec1;
	 assign temp[7] = !result[7]&&selec1||result[7]&&!selec1;
	 assign temp[8] = !result[8]&&selec1||result[8]&&!selec1;
   assign temp[9] = !result[9]&&selec1||result[9]&&!selec1;
   assign temp[10] = !result[10]&&selec1||result[10]&&!selec1;
	 assign temp[11] = !result[11]&&selec1||result[11]&&!selec1;



	// end
	// if ((selec1&&!add_sub)==1)
	// begin
	// 		assign  answer = -result;
	// // 		result = -result;
	// 	// temp = temp+tmptobeadded;
	// end

	assign sign12 = selec1&&!add_sub;
	add1toval a1(temp,sign12,answer);



endmodule

C.A./Adder Floating/Lab 0 Floating Point ADDer/Lab 0 again imporvement/expaddsubtb.v
// iverilog expaddsub.v expaddsubtb.v -o p4jul


module top;
reg [10:0] a;
reg [10:0] b;
reg add_sub;	  // if this is 1, add; else subtract
// input clk,
wire selec1;
wire [11:0] result;


addsub s1(a,b,add_sub,selec1,result);
// addsub s1(a,b,add_sub,select1,result);


initial
begin

a = 11'b00000011;b = 11'b00000010;add_sub = 1;#10;
a = 11'b00000101;b = 11'b00000110;add_sub = 1;#10;

a = 11'b00000111;b = 11'b00000111;add_sub = 1;#10;
a = 11'b00000111;b = 11'b00001111;add_sub = 0;#10;
a = 11'b00000111;b = 11'b00000111;add_sub = 1;#10;


a = 11'b00001111;b = 11'b00001010;add_sub = 0;#10;
a = 11'b11111100; b= 11'd252;add_sub = 1;#10;
a = 11'b11111110; b= 11'd752;add_sub = 1;#10;
a = 11'b11111101; b= 11'd52;add_sub = 1;#10;

a = 11'b11111100; b= 11'd255;add_sub = 0;#10;

a = 11'b11111110; b= 11'd22;add_sub = 1;#10;
a = 11'b10000000000; b= 11'b11111111111;add_sub = 0;#10;




end

initial
begin
// $monitor("time = %2d,")
$monitor("time = %2d,  addorsub=%d, a=%d, b=%d Ans=%d sign = %d", $time,add_sub,a, b,result,selec1);
$dumpfile("youmisswedupname.vcd");
$dumpvars(0,top);
end



endmodule // top

C.A./Adder Floating/Lab 0 Floating Point ADDer/Main Work/youmisswedupname.vcd
$date
	Fri Jan 31 05:58:15 2020
$end
$version
	Icarus Verilog
$end
$timescale
	1s
$end
$scope module top $end
$var wire 1 ! selec1 $end
$var wire 12 " result [11:0] $end
$var reg 11 # a [10:0] $end
$var reg 1 $ add_sub $end
$var reg 11 % b [10:0] $end
$scope module s1 $end
$var wire 1 $ add_sub $end
$var wire 11 & dataa [10:0] $end
$var wire 11 ' datab [10:0] $end
$var wire 1 ! sign12 $end
$var wire 12 ( temp [11:0] $end
$var wire 12 ) answer [11:0] $end
$var reg 12 * result [11:0] $end
$var reg 1 + selec1 $end
$scope module a1 $end
$var wire 12 , asnwer [11:0] $end
$var wire 12 - dataa [11:0] $end
$var wire 1 ! e1nable $end
$var reg 12 . result [11:0] $end
$upscope $end
$upscope $end
$upscope $end
$enddefinitions $end
#0
$dumpvars
b101 .
b101 -
b101 ,
0+
b101 *
b101 )
b101 (
b10 '
b11 &
b10 %
1$
b11 #
b101 "
0!
$end
#10
b1011 "
b1011 )
b1011 ,
b1011 .
b1011 (
b1011 -
b1011 *
b110 %
b110 '
b101 #
b101 &
#20
b1110 "
b1110 )
b1110 ,
b1110 .
b1110 (
b1110 -
b1110 *
b111 %
b111 '
b111 #
b111 &
#30
b111 (
b111 -
b1000 "
b1000 )
b1000 ,
b1000 .
1!
1+
b111111111000 *
0$
b1111 %
b1111 '
#40
b1110 (
b1110 -
b1110 "
b1110 )
b1110 ,
b1110 .
0!
0+
b1110 *
1$
b111 %
b111 '
#50
b101 "
b101 )
b101 ,
b101 .
b101 (
b101 -
b101 *
0$
b1010 %
b1010 '
b1111 #
b1111 &
#60
b111111000 "
b111111000 )
b111111000 ,
b111111000 .
b111111000 (
b111111000 -
b111111000 *
1$
b11111100 %
b11111100 '
b11111100 #
b11111100 &
#70
b1111101110 "
b1111101110 )
b1111101110 ,
b1111101110 .
b1111101110 (
b1111101110 -
b1111101110 *
b1011110000 %
b1011110000 '
b11111110 #
b11111110 &
#80
b100110001 "
b100110001 )
b100110001 ,
b100110001 .
b100110001 (
b100110001 -
b100110001 *
b110100 %
b110100 '
b11111101 #
b11111101 &
#90
b10 (
b10 -
b11 "
b11 )
b11 ,
b11 .
1!
1+
b111111111101 *
0$
b11111111 %
b11111111 '
b11111100 #
b11111100 &
#100
b100010100 (
b100010100 -
b100010100 "
b100010100 )
b100010100 ,
b100010100 .
0!
0+
b100010100 *
1$
b10110 %
b10110 '
b11111110 #
b11111110 &
#110
b1111111110 (
b1111111110 -
b1111111111 "
b1111111111 )
b1111111111 ,
b1111111111 .
1!
1+
b110000000001 *
0$
b11111111111 %
b11111111111 '
b10000000000 #
b10000000000 &
